ppagent
