Metadata-Version: 1.0
Name: ppagent
Version: 0.3.4
Summary: A statistics collection agent for powerpool mining server
Home-page: http://www.python.org/sigs/distutils-sig/
Author: Isaac Cook
Author-email: isaac@simpload.com
License: UNKNOWN
Platform: UNKNOWN
